README.md
setup.py
acrcloud/__init__.py
acrcloud/exceptions.py
python_acrcloud.egg-info/PKG-INFO
python_acrcloud.egg-info/SOURCES.txt
python_acrcloud.egg-info/dependency_links.txt
python_acrcloud.egg-info/requires.txt
python_acrcloud.egg-info/top_level.txt