Metadata-Version: 1.0
Name: python-acrcloud
Version: 1.1
Summary: Detects the songs from an audio
Home-page: https://github.com/An0nimia/acrcloud
Author: An0nimia
Author-email: An0nimia@protonmail.com
License: CC BY-NC-SA 4.0
Platform: UNKNOWN
